hwtest/__init__.py
hwtest/component.py
hwtest/controller.py
hwtest/driver.py
hwtest/influxdb.py
hwtest/logging.py
hwtest/telemetry.py
hwtest-0.0.1.dist-info/METADATA
hwtest-0.0.1.dist-info/WHEEL
hwtest-0.0.1.dist-info/licenses/LICENSE.txt
hwtest-0.0.1.dist-info/RECORD
