Metadata-Version: 2.1
Name: hwtest
Version: 0.0.1
Summary: A framework for testing hardware
License-File: LICENSE.txt
Requires-Python: >=3.7
Provides-Extra: influxdb
Requires-Dist: influxdb-client[ciso]; extra == 'influxdb'
